{
  "2025": {
    "71": {
      "Flamengo": {
        "results": ["D", "E: 1x1"],
        "next_opponent": "Palmeiras",
        "opponent_table": "Top 4",
        "form_opponent": "V, V",
        "position": 4,
        "points": 32,
        "avg_goals": 1.9,
        "avg_corners": 6.4,
        "home_away": "Casa",
        "injuries": "Nenhum",
        "new_coach": false,
        "last_5_summary": "1V, 1E, 3D"
      },
      "São Paulo": {
        "results": ["E: 0x0", "D"],
        "next_opponent": "Palmeiras",
        "opponent_table": "Top 4",
        "form_opponent": "V, V",
        "position": 9,
        "points": 24,
        "avg_goals": 1.3,
        "avg_corners": 4.7,
        "home_away": "Fora",
        "injuries": "1 titular",
        "new_coach": false,
        "last_5_summary": "1V, 2E, 2D"
      }
    }
  }
}
